wind_power_timeseries/__init__.py
wind_power_timeseries/compute.py
wind_power_timeseries/download.py
wind_power_timeseries/powercurves/DTU_10MW_178_RWT_v1.csv
wind_power_timeseries/powercurves/IEA_10MW_198_RWT.csv
wind_power_timeseries/powercurves/IEA_15MW_240_RWT.csv
wind_power_timeseries/powercurves/NREL_5MW_126_RWT_corrected.csv
wind_power_timeseries/powercurves/wind_powercurves_tradewind.csv
wind_power_timeseries/sample.py
wind_power_timeseries/utils.py
wind_power_timeseries-0.6.1.dist-info/METADATA
wind_power_timeseries-0.6.1.dist-info/WHEEL
wind_power_timeseries-0.6.1.dist-info/licenses/LICENSE
wind_power_timeseries-0.6.1.dist-info/RECORD
