Metadata-Version: 2.4
Name: wind_power_timeseries
Version: 0.6.1
Summary: Package for downloading timeseries data and convert to generated power
License-Expression: MIT
License-File: LICENSE
Author: Harald G Svendsen
Author-email: harald.svendsen@sintef.no
Requires-Python: >=3.11
Classifier: Development Status :: 4 - Beta
Classifier: Programming Language :: Python
Requires-Dist: cdsapi (>=0.7.5,<0.8.0)
Requires-Dist: metocean-api (>=1.1.10)
Requires-Dist: numpy (>=2.2.3)
Requires-Dist: pandas (>=2.2.3)
Requires-Dist: scipy (>=1.15.2)
